insertmendoza/__init__.py
insertmendoza/client.py
insertmendoza-1.0.13.dist-info/METADATA
insertmendoza-1.0.13.dist-info/WHEEL
insertmendoza-1.0.13.dist-info/top_level.txt
insertmendoza-1.0.13.dist-info/RECORD
