Metadata-Version: 2.1
Name: insertmendoza
Version: 1.0.13
Summary: Cliente para sarys 6.x
Home-page: https://gitlab.com/njavilas2015/sdk-python-v6
Author: Insert Mendoza
Author-email: njavilas@insertmendoza.com.ar
License: UNKNOWN
Platform: UNKNOWN
Classifier: Programming Language :: Python :: 3
Classifier: License :: OSI Approved :: MIT License
Classifier: Operating System :: OS Independent
Requires-Dist: requests
Requires-Dist: python-socketio
